LICENSE.txt
MANIFEST.in
README.rst
cryptoparams.py
setup.py
py_crypto_params.egg-info/PKG-INFO
py_crypto_params.egg-info/SOURCES.txt
py_crypto_params.egg-info/dependency_links.txt
py_crypto_params.egg-info/requires.txt
py_crypto_params.egg-info/top_level.txt