Metadata-Version: 1.1
Name: py-crypto-params
Version: 1.0.0
Summary: Utility function to encrypt - decrypt string using AES symmetric algorithm that is compatible with crypto-js
Home-page: https://github.com/torre76/py-crypto-params
Author: Gian Luca Dalla Torre
Author-email: gianluca.dallatorre@gmail.com
License: LICENSE.txt
Download-URL: https://github.com/torre76/py-crypto-params/tarball/1.0.0
Keywords: crypto-js crypto aes parameters encryption
Platform: UNKNOWN
Classifier: Development Status :: 5 - Production/Stable
Classifier: License :: OSI Approved :: GNU Lesser General Public License v3 or later (LGPLv3+)
Classifier: Programming Language :: Python :: 2.6
Classifier: Programming Language :: Python :: 2.7
Classifier: Programming Language :: Python :: 3.4
Classifier: Programming Language :: Python :: 3.5
